cpg_cdm_agg/__init__.py
cpg_cdm_agg/aggregations.py
cpg_cdm_agg/executor.py
cpg_cdm_agg/py.typed
cpg_cdm_agg-1.0.0.dist-info/licenses/LICENSE
cpg_cdm_agg-1.0.0.dist-info/METADATA
cpg_cdm_agg-1.0.0.dist-info/WHEEL
cpg_cdm_agg-1.0.0.dist-info/top_level.txt
cpg_cdm_agg-1.0.0.dist-info/RECORD
