Metadata-Version: 2.4
Name: cpg-cdm-agg
Version: 1.0.0
Summary: A Python package for creating Gold layer Iceberg tables from Silver layer data in Snowflake using Snowpark Python
Author-email: Your Name <your.email@example.com>
Maintainer-email: Your Name <your.email@example.com>
License: MIT
Project-URL: Homepage, https://github.com/yourusername/cpg-cdm-agg
Project-URL: Documentation, https://github.com/yourusername/cpg-cdm-agg#readme
Project-URL: Repository, https://github.com/yourusername/cpg-cdm-agg
Project-URL: Issues, https://github.com/yourusername/cpg-cdm-agg/issues
Keywords: snowflake,snowpark,data-engineering,etl,gold-layer,iceberg,data-warehouse,aggregations,cpg
Classifier: Development Status :: 4 - Beta
Classifier: Intended Audience :: Developers
Classifier: Intended Audience :: Science/Research
Classifier: License :: OSI Approved :: MIT License
Classifier: Operating System :: OS Independent
Classifier: Programming Language :: Python :: 3
Classifier: Programming Language :: Python :: 3.8
Classifier: Programming Language :: Python :: 3.9
Classifier: Programming Language :: Python :: 3.10
Classifier: Programming Language :: Python :: 3.11
Classifier: Topic :: Database
Classifier: Topic :: Scientific/Engineering
Requires-Python: >=3.8
License-File: LICENSE
Requires-Dist: snowflake-snowpark-python>=1.0.0
Provides-Extra: dev
Requires-Dist: pytest>=7.0.0; extra == "dev"
Requires-Dist: pytest-cov>=4.0.0; extra == "dev"
Requires-Dist: black>=23.0.0; extra == "dev"
Requires-Dist: isort>=5.12.0; extra == "dev"
Requires-Dist: mypy>=1.0.0; extra == "dev"
Dynamic: license-file
